esmbc
