Metadata-Version: 1.1
Name: esmbc
Version: 0.4
Summary: EVE Online Ship Maintenance Bay Calculator
Home-page: https://github.com/stuartdb/esmbc
Author: Stuart Baker
Author-email: sdb@stuartdb.com
License: GPL3
Platform: any
Classifier: Development Status :: 4 - Beta
Classifier: Environment :: Console
Classifier: Intended Audience :: End Users/Desktop
Classifier: Operating System :: OS Independent
Classifier: Programming Language :: Python :: 3.3
Classifier: Programming Language :: Python :: 2.7
Classifier: License :: OSI Approved :: GNU General Public License v3 (GPLv3)
Classifier: Topic :: Games/Entertainment
